pynsitu/__init__.py
pynsitu/drifters.py
pynsitu/events.py
pynsitu/geo.py
pynsitu/maps.py
pynsitu/movies.py
pynsitu/pynsitu.yaml
pynsitu/seawater.py
pynsitu/tides.py
pynsitu/tseries.py
pynsitu-0.0.3.dist-info/METADATA
pynsitu-0.0.3.dist-info/WHEEL
pynsitu-0.0.3.dist-info/licenses/LICENSE
pynsitu-0.0.3.dist-info/RECORD
